semantikon/__init__.py
semantikon/_version.py
semantikon/converter.py
semantikon/datastructure.py
semantikon/metadata.py
semantikon/ontology.py
semantikon/qudt.py
semantikon/visualize.py
semantikon/workflow.py
semantikon/data/qudt.ttl
semantikon-0.0.26.dist-info/METADATA
semantikon-0.0.26.dist-info/WHEEL
semantikon-0.0.26.dist-info/licenses/LICENSE
semantikon-0.0.26.dist-info/RECORD
