Metadata-Version: 2.4
Name: semantikon
Version: 0.0.26
Summary: semantikon - Ontological type system
Project-URL: Homepage, https://pyiron.org/
Project-URL: Documentation, https://semantikon.readthedocs.io
Project-URL: Repository, https://github.com/pyiron/semantikon
Author-email: Sam Waseda <waseda@mpie.de>
License: BSD 3-Clause License
License-File: LICENSE
Keywords: pyiron
Classifier: Development Status :: 3 - Alpha
Classifier: Intended Audience :: Science/Research
Classifier: License :: OSI Approved :: BSD License
Classifier: Operating System :: OS Independent
Classifier: Programming Language :: Python :: 3.11
Classifier: Programming Language :: Python :: 3.12
Classifier: Programming Language :: Python :: 3.13
Classifier: Programming Language :: Python :: 3.14
Classifier: Topic :: Scientific/Engineering
Requires-Python: <3.15,>=3.10
Requires-Dist: graphviz<=0.21,>=0.20.3
Requires-Dist: networkx<3.5.0,>=3.4.2
Requires-Dist: numpy<2.4.0,>=1.26.3
Requires-Dist: owlrl<7.2.0,>=7.1.2
Requires-Dist: pint<=0.25.2,>=0.23
Requires-Dist: pyshacl<=0.30.1,>=0.30.0
Requires-Dist: rdflib<7.5.0,>=7.1.1
Requires-Dist: requests<2.33.0,>=2.28.0
Requires-Dist: typeguard<4.5.0,>=4.0.0
